frony_document_processor/chunker.py
frony_document_processor/embedder.py
frony_document_processor/parser.py
frony_document_processor-0.5.0.dist-info/METADATA
frony_document_processor-0.5.0.dist-info/WHEEL
frony_document_processor-0.5.0.dist-info/top_level.txt
frony_document_processor-0.5.0.dist-info/RECORD
